odoo8_addon_base_view_inheritance_extension-8.0.1.1.0-nspkg.pth
odoo_addons/base_view_inheritance_extension/README.rst
odoo_addons/base_view_inheritance_extension/__init__.py
odoo_addons/base_view_inheritance_extension/__openerp__.py
odoo_addons/base_view_inheritance_extension/demo/ir_ui_view.xml
odoo_addons/base_view_inheritance_extension/i18n/base_view_inheritance_extension.pot
odoo_addons/base_view_inheritance_extension/i18n/ca.po
odoo_addons/base_view_inheritance_extension/i18n/de.po
odoo_addons/base_view_inheritance_extension/i18n/it.po
odoo_addons/base_view_inheritance_extension/i18n/nl.po
odoo_addons/base_view_inheritance_extension/i18n/pt_BR.po
odoo_addons/base_view_inheritance_extension/i18n/sl.po
odoo_addons/base_view_inheritance_extension/i18n/tr.po
odoo_addons/base_view_inheritance_extension/models/__init__.py
odoo_addons/base_view_inheritance_extension/models/ir_ui_view.py
odoo_addons/base_view_inheritance_extension/models/res_users.py
odoo_addons/base_view_inheritance_extension/static/description/icon.png
odoo_addons/base_view_inheritance_extension/tests/__init__.py
odoo_addons/base_view_inheritance_extension/tests/test_base_view_inheritance_extension.py
odoo8_addon_base_view_inheritance_extension-8.0.1.1.0.dist-info/METADATA
odoo8_addon_base_view_inheritance_extension-8.0.1.1.0.dist-info/WHEEL
odoo8_addon_base_view_inheritance_extension-8.0.1.1.0.dist-info/namespace_packages.txt
odoo8_addon_base_view_inheritance_extension-8.0.1.1.0.dist-info/top_level.txt
odoo8_addon_base_view_inheritance_extension-8.0.1.1.0.dist-info/RECORD
